Workbook

Sheet Hoja1
A1: REVISION DE TALON DE CHEQUES
A2: MAESTRO
A3: RFC | C3: NOMBRE
A4: QNA TALON | C4: 09-2026 | D4: FECHA TALON | E4: 46157
A5: INGRESOS | D5: DEDUCCIONES
A6: =+Hoja2!A6 -> E4 | B6: =+Hoja2!B20 -> 0 | C6: =+SUM(B6:B15) -> 0 | D6: DESCUENTOS
A7: =+Hoja2!A7 -> E3 | B7: =+Hoja2!B21 -> 0 | D7: SALDO | E7: =+C6-E6 -> 0
A8: =+Hoja2!A8 -> Q | B8: 0 | D8: TOTAL PARA VENTA 70% | E8: =+C6*0.7 -> 0
A9: =+Hoja2!A9 -> CP | B9: 0
A10: =+Hoja2!A10 -> 7 | B10: 0 | D10: SALDO AL 70% | E10: =+E8-E6 -> 0
A11: =+Hoja2!A11 -> CT | B11: 0 | D11: SALDO MAS ABONOS AL 70%
A12: =+Hoja2!A12 -> 7B | B12: 0 | D12: =+E10+B25 -> 0
A13: =+Hoja2!A13 -> E9 | B13: 0 | D13: SALDO MAS ABONO A TERMINAR AL 100
A14: =+Hoja2!A14 -> SG | B14: 0
A15: =+Hoja2!A15 -> O1 | B15: 0 | D15: =+E7+B25 -> 0
A16: DC TALON | C16: DC SISTEMA | E16: =+B16-D16 -> 0
A17: VENDEDOR | B17: RECUPERACIÓN (Abonos a Liquidar) | D17: VENTA(entrante o en relcmacion)
B19: FOLIO | C19: SALDO | D19: FOLIO | E19: SALDO
B24: Total a Recuperar | D24: Total a VENDER
B25: =+SUM(C20:C23) -> 0 | D25: =+SUM(E20:E23) -> 0
B27: SALDO AL 70 | D27: SALDO AL 100
B28: =+D12-D25 -> 0 | D28: =+D15-D25 -> 0
A30: REVISION DEL CLIENTE
A31: PROMOTOR | B31: =+A18 -> 0
A32: NOMBRE: | B32: =+D3 -> 0
A33: RFC: | B33: =+B3 -> 0
A34: LIQUIDEZ | B34: =+D28 -> 0
A35: QNA | B35: =+C4 -> 09-2026
A36: COMENTARIO
A40: FECHA | B40: =+TODAY() -> 46176

Sheet Hoja2
A1: CONCEPTOS DE INGRESOS PARA CALCULAR LA CAPACIDAD DE PAGO | J1: D=DESCUENTOS
A2: DEFICINION DE DESCUENTOS | C2: 07= SUELDO | D2: A,Q=QUINQUENIO | F2: E9=ASIGNACION DOCENTE | I2: E3,E4=ARRAIGO | K2: CP=COMPENSASION PROV
C3: CT= COMPENSASION TEM
A5: CODIGO | B5: ABONOS | C5: CODIGO | D5: ABONOS | E5: CODIGO | F5: ABONOS | G5: CODIGO | H5: ABONOS | I5: CODIGO | J5: ABONOS | K5: CODIGO | L5: ABONOS | M5: CODIGO | N5: ABONOS | O5: CODIGO | P5: ABONOS
A6: E4 | C6: =+A6 -> E4 | E6: =+C6 -> E4 | G6: =+E6 -> E4 | I6: =+G6 -> E4 | K6: =+I6 -> E4 | M6: =+K6 -> E4 | O6: =+M6 -> E4
A7: E3 | C7: =+A7 -> E3 | E7: =+C7 -> E3 | G7: =+E7 -> E3 | I7: =+G7 -> E3 | K7: =+I7 -> E3 | M7: =+K7 -> E3 | O7: =+M7 -> E3
A8: Q | C8: =+A8 -> Q | E8: =+C8 -> Q | G8: =+E8 -> Q | I8: =+G8 -> Q | K8: =+I8 -> Q | M8: =+K8 -> Q | O8: =+M8 -> Q
A9: CP | C9: =+A9 -> CP | E9: =+C9 -> CP | G9: =+E9 -> CP | I9: =+G9 -> CP | K9: =+I9 -> CP | M9: =+K9 -> CP | O9: =+M9 -> CP
A10: 7 | C10: =+A10 -> 7 | E10: =+C10 -> 7 | G10: =+E10 -> 7 | I10: =+G10 -> 7 | K10: =+I10 -> 7 | M10: =+K10 -> 7 | O10: =+M10 -> 7
A11: CT | C11: =+A11 -> CT | E11: =+C11 -> CT | G11: =+E11 -> CT | I11: =+G11 -> CT | K11: =+I11 -> CT | M11: =+K11 -> CT | O11: =+M11 -> CT
A12: 7B | C12: =+A12 -> 7B | E12: =+C12 -> 7B | G12: =+E12 -> 7B | I12: =+G12 -> 7B | K12: =+I12 -> 7B | M12: =+K12 -> 7B | O12: =+M12 -> 7B
A13: E9 | C13: =+A13 -> E9 | E13: =+C13 -> E9 | G13: =+E13 -> E9 | I13: =+G13 -> E9 | K13: =+I13 -> E9 | M13: =+K13 -> E9 | O13: =+M13 -> E9
A14: SG | C14: =+A14 -> SG | E14: =+C14 -> SG | G14: =+E14 -> SG | I14: =+G14 -> SG | K14: =+I14 -> SG | M14: =+K14 -> SG | O14: =+M14 -> SG
A15: O1 | C15: =+A15 -> O1 | E15: =+C15 -> O1 | G15: =+E15 -> O1 | I15: =+G15 -> O1 | K15: =+I15 -> O1 | M15: =+K15 -> O1 | O15: =+M15 -> O1
A16: D | C16: =+A16 -> D | E16: =+C16 -> D | G16: =+E16 -> D | I16: =+G16 -> D | K16: =+I16 -> D | M16: =+K16 -> D | O16: =+M16 -> D
A17: DC | C17: =+A17 -> DC | E17: =+C17 -> DC | G17: =+E17 -> DC | I17: =+G17 -> DC | K17: =+I17 -> DC | M17: =+K17 -> DC | O17: =+M17 -> DC
A18: total | D18: =+SUM(D6:D15)-D16 -> 0 | F18: =+SUM(F6:F15)-F16 -> 0 | H18: =+SUM(H6:H15)-H16 -> 0 | J18: =+SUM(J6:J15)-J16 -> 0 | L18: =+SUM(L6:L15)-L16 -> 0 | N18: =+SUM(N6:N15)-N16 -> 0 | P18: =+SUM(P6:P15)-P16 -> 0
A19: TOTAL
A20: =+A6 -> E4 | B20: =+B6+D6+F6+J6+H6+L6+N6+P6 -> 0
A21: =+A7 -> E3 | B21: =+B7+D7+F7+J7+H7+L7+N7+P7 -> 0
A22: =+A8 -> Q | B22: =+B8+D8+F8+J8+H8+L8+N8+P8 -> 0
A23: =+A9 -> CP | B23: =+B9+D9+F9+J9+H9+L9+N9+P9 -> 0
A24: =+A10 -> 7 | B24: =+B10+D10+F10+J10+H10+L10+N10+P10 -> 0
A25: =+A11 -> CT | B25: =+B11+D11+F11+J11+H11+L11+N11+P11 -> 0
A26: =+A12 -> 7B | B26: =+B12+D12+F12+J12+H12+L12+N12+P12 -> 0
A27: =+A13 -> E9 | B27: =+B13+D13+F13+J13+H13+L13+N13+P13 -> 0
A28: =+A14 -> SG | B28: =+B14+D14+F14+J14+H14+L14+N14+P14 -> 0
A29: =+A15 -> O1 | B29: =+B15+D15+F15+J15+H15+L15+N15+P15 -> 0
A30: =+A16 -> D | B30: =+B16+D16+F16+J16+H16+L16+N16+P16 -> 0
A31: =+A17 -> DC | B31: =+B17+D17+F17+J17+H17+L17+N17+P17 -> 0

Sheet Hoja3
B1: 28254.2
A2: =+B1-B2 -> 15990.28 | B2: 12263.92
